README.md
setup.py
conductor/ConductorScheduler.py
conductor/ConductorWorker.py
conductor/__init__.py
conductor/conductor.py
conductor/models.py
conductor/worker.py
conductorpyworker.egg-info/PKG-INFO
conductorpyworker.egg-info/SOURCES.txt
conductorpyworker.egg-info/dependency_links.txt
conductorpyworker.egg-info/requires.txt
conductorpyworker.egg-info/top_level.txt