Metadata-Version: 1.0
Name: conductorpyworker
Version: 0.0.1
Summary: conductor python sdk
Home-page: UNKNOWN
Author: wyc
Author-email: UNKNOWN
License: MIT License
Keywords: conductor python sdk
Platform: any
